imusensor/__init__.py
imusensor/MPU9250/MPU9250.py
imusensor/MPU9250/__init__.py
imusensor/MPU9250/config.py
imusensor/filters/__init__.py
imusensor/filters/complimentary.py
imusensor/filters/kalman.py
imusensor/filters/madgwick.py
imusensor-1.0.1.dist-info/LICENSE
imusensor-1.0.1.dist-info/METADATA
imusensor-1.0.1.dist-info/WHEEL
imusensor-1.0.1.dist-info/top_level.txt
imusensor-1.0.1.dist-info/RECORD
