Metadata-Version: 2.1
Name: imusensor
Version: 1.0.1
Summary: Linking Raspberry pi with MPU9250
Home-page: https://github.com/niru-5/imu-mpu9250/tree/master
Author: Niranjan Kukkala
Author-email: niranjan.reddy.wo@gmail.com
License: UNKNOWN
Platform: UNKNOWN
Classifier: Programming Language :: Python :: 3
Classifier: License :: OSI Approved :: MIT License
Classifier: Operating System :: OS Independent
Requires-Python: >=3
